mock_data_generator/driver.py
mock_data_generator/generator/generate.py
mock_data_generator/generator/mappings.py
mock_data_generator/generator/misc.py
mock_data_generator/generator/output.py
mock_data_generator/generator/predefined.py
mock_data_generator/resources/config.ini
mock_data_generator/resources/schema.json
mock_data_generator/schema_handler/schema_validator.py
mock_data_generator/tests/fileutils_test.py
mock_data_generator/tests/schema_validator_test.py
mock_data_generator/tests/test.json
mock_data_generator/utils/constants.py
mock_data_generator/utils/fileutils.py
mock_data_generator-1.2.9.dist-info/LICENSE
mock_data_generator-1.2.9.dist-info/METADATA
mock_data_generator-1.2.9.dist-info/WHEEL
mock_data_generator-1.2.9.dist-info/entry_points.txt
mock_data_generator-1.2.9.dist-info/RECORD
