Metadata-Version: 2.1
Name: mock-data-generator
Version: 1.2.9
Summary: Generate mock data using json schema supplied. 
License: MIT
Author: Rahul Auti
Author-email: rahulsmtauti@gmail.com
Requires-Python: >=3.10,<4.0
Classifier: License :: OSI Approved :: MIT License
Classifier: Programming Language :: Python :: 3
Classifier: Programming Language :: Python :: 3.10
Classifier: Programming Language :: Python :: 3.11
Requires-Dist: faker (>=18.9.0,<19.0.0)
Requires-Dist: fastparquet (>=2023.4.0,<2024.0.0)
Requires-Dist: jsonschema (>=4.17.3,<5.0.0)
Requires-Dist: lxml (>=4.9.2,<5.0.0)
Requires-Dist: openpyxl (>=3.1.2,<4.0.0)
Requires-Dist: pandas (>=2.0.2,<3.0.0)
Requires-Dist: pyarrow (>=12.0.0,<13.0.0)
Requires-Dist: tqdm (>=4.65.0,<5.0.0)
